tjutils/__init__.py
tjutils/_modidx.py
tjutils/nbdev.py
tjutils/templates/nbdev/_quarto.yml
tjutils/templates/nbdev/github_actions/doc_deploy.yml
tjutils/templates/nbdev/github_actions/pkg_testing.yml
tjutils/templates/nbdev/gitignore
tjutils/templates/nbdev/setup.cfg
tjutils/templates/nbdev/theme/analytics.htm
tjutils/templates/nbdev/theme/logo/logo-banner.png
tjutils/templates/nbdev/theme/logo/logo-large.png
tjutils/templates/nbdev/theme/logo/logo-small.png
tjutils/templates/nbdev/theme/theme.htm
tjutils/templates/nbdev/theme/theme.scss
tjutils/templates/terraform/github_actions/tf_deploy.yml
tjutils/utils.py
tjutils-0.11.0.dist-info/METADATA
tjutils-0.11.0.dist-info/WHEEL
tjutils-0.11.0.dist-info/entry_points.txt
tjutils-0.11.0.dist-info/RECORD
