Metadata-Version: 2.1
Name: tjutils
Version: 0.11.0
Summary: Python Utilities for TJ P
Home-page: https://github.tjpalanca.com/tjutils-py
License: MIT
Keywords: tjpalanca,nbdev,utilities
Author: TJ P
Author-email: mail@tjpalanca.com
Requires-Python: >=3.9,<4.0
Classifier: Development Status :: 4 - Beta
Classifier: License :: OSI Approved :: MIT License
Classifier: Programming Language :: Python :: 3
Classifier: Programming Language :: Python :: 3.9
Classifier: Programming Language :: Python :: 3.10
Classifier: Programming Language :: Python :: 3.11
Classifier: Topic :: Utilities
Requires-Dist: GitPython (>=3.1.27,<4.0.0)
Requires-Dist: black[jupyter] (>=22.10.0,<23.0.0)
Requires-Dist: fastcore (>=1.5.27,<2.0.0)
Requires-Dist: flake8 (>=5.0.4,<6.0.0)
Requires-Dist: ipykernel (>=6.15.3,<7.0.0)
Requires-Dist: mypy (>=0.971,<0.972)
Requires-Dist: nbdev (>=2.3.7,<3.0.0)
Requires-Dist: tomli (>=2.0.1,<3.0.0)
Requires-Dist: tomlkit (>=0.11.5,<0.12.0)
Project-URL: Documentation, https://github.tjpalanca.com/tjutils-py
Project-URL: Repository, https://github.com/tjpalanca/tjutils-py.git
